oscg/__init__.py
oscg/cli.py
oscg/core.py
oscg/example.py
oscg/utils.py
oscg/templates/apikey.xml
oscg/templates/config.xml
oscg/templates/fw_admin.xml
oscg/templates/fw_wg.xml
oscg/templates/opt_dhcp.xml
oscg/templates/opt_if.xml
oscg/templates/wg_conf.xml
oscg/templates/wg_grp.xml
oscg/templates/wg_if.xml
opnsense_confgen-2.3.2.dist-info/LICENSE.txt
opnsense_confgen-2.3.2.dist-info/METADATA
opnsense_confgen-2.3.2.dist-info/WHEEL
opnsense_confgen-2.3.2.dist-info/entry_points.txt
opnsense_confgen-2.3.2.dist-info/top_level.txt
opnsense_confgen-2.3.2.dist-info/RECORD
