Metadata-Version: 2.1
Name: opnsense-confgen
Version: 2.3.2
Summary: Generate OPNsense configuration XML
Author: Malwarology LLC
Project-URL: Homepage, https://github.com/malwarology/opnsense-confgen
Project-URL: Issues, https://github.com/malwarology/opnsense-confgen/issues
Keywords: opnsense,configuration,firewall,install
Classifier: Development Status :: 5 - Production/Stable
Classifier: Environment :: Console
Classifier: Intended Audience :: Information Technology
Classifier: Intended Audience :: System Administrators
Classifier: License :: OSI Approved :: MIT License
Classifier: Natural Language :: English
Classifier: Operating System :: OS Independent
Classifier: Programming Language :: Python
Classifier: Programming Language :: Python :: 3
Classifier: Programming Language :: Python :: 3 :: Only
Classifier: Programming Language :: Python :: 3.12
Classifier: Topic :: Security
Classifier: Topic :: System :: Networking :: Firewalls
Classifier: Topic :: System :: Systems Administration
Classifier: Topic :: Text Processing :: Markup :: XML
Classifier: Topic :: Utilities
Requires-Python: >=3.12.3
License-File: LICENSE.txt
Requires-Dist: pynacl
Requires-Dist: pycdlib
